calculator_package_DOUG_HUNGWE/__init__.py
calculator_package_DOUG_HUNGWE/calculator.py
calculator_package_DOUG_HUNGWE-0.0.1.dist-info/LICENCE
calculator_package_DOUG_HUNGWE-0.0.1.dist-info/METADATA
calculator_package_DOUG_HUNGWE-0.0.1.dist-info/WHEEL
calculator_package_DOUG_HUNGWE-0.0.1.dist-info/top_level.txt
calculator_package_DOUG_HUNGWE-0.0.1.dist-info/RECORD
