Metadata-Version: 2.1
Name: calculator_package_DOUG_HUNGWE
Version: 0.0.1
Summary: A simple calculator package
Author-email: Douglas Hungwe <doughungwe@gmail.com>
Classifier: Programming Language :: Python :: 3
Classifier: License :: OSI Approved :: MIT License
Classifier: Operating System :: OS Independent
Requires-Python: >=3.8
License-File: LICENCE
